pexit/__init__.py
pexit/main.py
pexit/pexit
pexit/pexit.c
pexit-0.1.0.dist-info/licenses/LICENSE
pexit-0.1.0.dist-info/METADATA
pexit-0.1.0.dist-info/WHEEL
pexit-0.1.0.dist-info/entry_points.txt
pexit-0.1.0.dist-info/top_level.txt
pexit-0.1.0.dist-info/RECORD
