Metadata-Version: 2.4
Name: pexit
Version: 0.1.0
Summary: A CLI tool to exit any process with arbitrary exit code
Author-email: John Ao <johnao73thu@gmail.com>
License: Copyright (c) 2025 John Ao
Project-URL: Homepage, https://github.com/John-Ao/pexit
Keywords: exit,kill,process
Classifier: License :: OSI Approved :: MIT License
Classifier: Programming Language :: C
Classifier: Programming Language :: Python
Classifier: Programming Language :: Python :: 3
Requires-Python: >=3.0
License-File: LICENSE
Dynamic: license-file
